[
    {
        "school": "安徽省合肥市四十六中学",
        "grade": "高二年级",
        "class": "重点班（2）班",
        "name": "诸葛亮",
        "number": "300045",
        "operate": "删除"
    },
    {
        "school": "安徽省合肥市四十六中学",
        "grade": "高二年级",
        "class": "重点班（2）班",
        "name": "诸葛亮",
        "number": "300045",
        "operate": "删除"
    },
    {
        "school": "安徽省合肥市四十六中学",
        "grade": "高二年级",
        "class": "重点班（2）班",
        "name": "诸葛亮",
        "number": "300045",
        "operate": "删除"
    },
    {
        "school": "安徽省合肥市四十六中学",
        "grade": "高二年级",
        "class": "重点班（2）班",
        "name": "诸葛亮",
        "number": "300045",
        "operate": "删除"
    },
    {
        "school": "安徽省合肥市四十六中学",
        "grade": "高二年级",
        "class": "重点班（2）班",
        "name": "诸葛亮",
        "number": "300045",
        "operate": "删除"
    },
    {
        "school": "安徽省合肥市四十六中学",
        "grade": "高二年级",
        "class": "重点班（2）班",
        "name": "诸葛亮",
        "number": "300045",
        "operate": "删除"
    }
]